{
  "sections": {
    "main-titles": {
      "type": "main-titles",
      "settings": {
        "main_title": "Bowmont",
        "subtitle": "",
        "title_1": "",
        "body_content_1": "Our quest for a British Merino supply chain started back in 2005. It led us to Lesley Prior, the guardian of the last twenty-eight Bowmont Merino sheep on the planet; a breed capable of producing a fine Merino wool but with the hardiness to survive on these shores.",
        "title_2": "",
        "body_content_2": "",
        "title_3": "",
        "body_content_3": ""
      }
    },
    "1639652210a4ffe9b8": {
      "type": "large-feature-a",
      "settings": {
        "desktop_image": "shopify:\/\/shop_images\/bowmont-large-image.jpg",
        "mobile_image": "shopify:\/\/shop_images\/bowmont-mobile-hero.jpg",
        "video_url": "https:\/\/player.vimeo.com\/external\/363846211.hd.mp4?s=9ce656bed4864671522da58adee6569ff23e946e&profile_id=175",
        "caption": ""
      }
    },
    "16390492346014eb34": {
      "type": "body-text",
      "blocks": {
        "6d3b0749-6329-4cf2-8696-efd84797cdb5": {
          "type": "body",
          "settings": {
            "body": "<p>The Bowmont Project is a unique story that celebrates our love affair with wool, champions local British manufacturing and supply chain, and showcases our commitment to always strive for the best in our products.<\/p><p>Exclusive to Finisterre, our Bowmont flock now numbers over 300 sheep, providing the pinnacle of our wool offering.<\/p><p><em>Read the full story on <\/em><a href=\"https:\/\/finisterre.com\/blogs\/broadcast\/the-bowmont-project-unique-british-merino\" title=\"The Bowmont Project: Unique British Merino | Finisterre\"><em>The Broadcast...<\/em><\/a><\/p>"
          }
        }
      },
      "block_order": [
        "6d3b0749-6329-4cf2-8696-efd84797cdb5"
      ],
      "settings": {
      }
    },
    "1642775446de51df8c": {
      "type": "guide-products",
      "blocks": {
        "8ab5232b-8e69-4c83-acb2-a3e874e7a024": {
          "type": "product",
          "settings": {
            "image": "shopify:\/\/shop_images\/womens_bowmont_jumper_front.jpg",
            "title": "Women's Bowmont Jumper",
            "text": "",
            "button_text": "Shop here",
            "link": "shopify:\/\/products\/womens-wool-bowmont-jumper-navy-ecru"
          }
        },
        "aed27823-0ee9-4293-a105-d78db352cadf": {
          "type": "product",
          "settings": {
            "image": "shopify:\/\/shop_images\/mens_bowmont_jumper_front.jpg",
            "title": "Men's Bowmont Jumper",
            "text": "",
            "button_text": "Shop here",
            "link": "shopify:\/\/products\/mens-wool-bowmont-jumper-navy-ecru"
          }
        }
      },
      "block_order": [
        "8ab5232b-8e69-4c83-acb2-a3e874e7a024",
        "aed27823-0ee9-4293-a105-d78db352cadf"
      ],
      "settings": {
      }
    },
    "16427758801f0d1b03": {
      "type": "body-text",
      "blocks": {
        "885ee114-531e-4f83-bd78-812938df601c": {
          "type": "title",
          "settings": {
            "title": "Photos from the farm"
          }
        }
      },
      "block_order": [
        "885ee114-531e-4f83-bd78-812938df601c"
      ],
      "settings": {
      }
    },
    "1639049548fe89cefb": {
      "type": "double-medium-feature",
      "blocks": {
        "27ac6b12-155c-4677-82d0-c0ab42ce0a63": {
          "type": "image_block",
          "settings": {
            "image_1": "shopify:\/\/shop_images\/bowmont-1_7519415b-6e94-49e5-8ea6-17a62429bab8.jpg",
            "caption_1": "",
            "image_2": "shopify:\/\/shop_images\/bowmont-2.jpg",
            "caption_2": ""
          }
        }
      },
      "block_order": [
        "27ac6b12-155c-4677-82d0-c0ab42ce0a63"
      ],
      "settings": {
        "title": ""
      }
    },
    "1638962053c812c148": {
      "type": "double-medium-feature",
      "blocks": {
        "f5902a35-64bb-41ca-9fe7-47460372ea14": {
          "type": "image_block",
          "settings": {
            "image_1": "shopify:\/\/shop_images\/bowmont-3.jpg",
            "caption_1": "",
            "image_2": "shopify:\/\/shop_images\/bowmont-4.jpg",
            "caption_2": ""
          }
        }
      },
      "block_order": [
        "f5902a35-64bb-41ca-9fe7-47460372ea14"
      ],
      "settings": {
        "title": ""
      }
    },
    "16396539651c00601a": {
      "type": "double-medium-feature",
      "blocks": {
        "62ee262f-cfc7-41f4-b5d2-77e173d33cd2": {
          "type": "image_block",
          "settings": {
            "image_1": "shopify:\/\/shop_images\/bowmont-5.jpg",
            "caption_1": "",
            "image_2": "shopify:\/\/shop_images\/bowmont-7.jpg",
            "caption_2": ""
          }
        }
      },
      "block_order": [
        "62ee262f-cfc7-41f4-b5d2-77e173d33cd2"
      ],
      "settings": {
        "title": ""
      }
    }
  },
  "order": [
    "main-titles",
    "1639652210a4ffe9b8",
    "16390492346014eb34",
    "1642775446de51df8c",
    "16427758801f0d1b03",
    "1639049548fe89cefb",
    "1638962053c812c148",
    "16396539651c00601a"
  ]
}