{
  "sections": {
    "main-titles": {
      "type": "main-titles",
      "settings": {
        "main_title": "",
        "subtitle": "Adapting any wetsuit, from any brand, for any age and ability.",
        "title_1": "",
        "body_content_1": "",
        "title_2": "",
        "body_content_2": "",
        "title_3": "",
        "body_content_3": ""
      }
    },
    "16409455489a885bbc": {
      "type": "large-feature-a",
      "settings": {
        "desktop_image": "shopify:\/\/shop_images\/wetsuit-project-andrew-landscape.jpg",
        "mobile_image": "shopify:\/\/shop_images\/wetsuit-project-andrew.jpg",
        "video_url": "https:\/\/player.vimeo.com\/external\/639132497.hd.mp4?s=292a41380ccd04bca4b628d3b003d59e17364c99&profile_id=169",
        "caption": ""
      }
    },
    "1640945552a6004e0a": {
      "type": "body-text",
      "blocks": {
        "02ae8172-a107-40ec-a4f0-8bf1bba1d364": {
          "type": "body",
          "settings": {
            "body": "<p>Over our first ever Blue Friday weekend, we raised an incredible £14,120 for the Finisterre Foundation Wetsuit Project, to adapt wetsuits for those who face barriers in accessing the sea. Thank You. <\/p><p>A connection to the sea can bring untold mental and physical health benefits, but for some there are barriers to accessing those benefits. The Wetsuit Project has smashed its funding target, meaning we can immediately begin adapting wetsuits to get people in the water.<\/p>"
          }
        }
      },
      "block_order": [
        "02ae8172-a107-40ec-a4f0-8bf1bba1d364"
      ],
      "settings": {
      }
    },
    "16409461148f1ff1bd": {
      "type": "hero",
      "settings": {
        "desktop_image": "shopify:\/\/shop_images\/wetsuit-project-finisterre-foundation-landscape.jpg",
        "mobile_image": "shopify:\/\/shop_images\/wetsuit-project-finisterre-foundation.jpg",
        "alt": "",
        "video_url": "",
        "text": "",
        "anchor": ""
      }
    },
    "1640946239e9f0e095": {
      "type": "pull-quote",
      "settings": {
        "quote": "<p><em>“I don’t think anyone finds wetsuits a party to get in and out of, but for me it was a bit more of a struggle! Adding more mobility and wider entry points for my wrists and ankles, made a huge difference to getting ready, meaning I get to spend more time enjoying the freedom the sea gives me.”<\/em><\/p>",
        "credit": "- Andrew Birkett"
      }
    },
    "1640946277aef9214f": {
      "type": "pull-quote-in-adventure-feature",
      "settings": {
        "image": "shopify:\/\/shop_images\/wetsuit-project-foundation-logo_70803476-13d5-4538-a1e8-e1b5f4b4bb72.png",
        "caption": "",
        "overline": "Apply for a Wetsuit Adaption",
        "body": "Championing equal access to the ocean for all, the Finisterre Foundation aims to break down barriers for anyone who wishes to enjoy the water.  The Wetsuit Project is as an evergreen initiative that supports our diverse community of ocean lovers.",
        "button_text": "Wetsuit Project Application Policy",
        "button_link": "shopify:\/\/pages\/ambassador-easkey-britton"
      }
    },
    "164094628093a46417": {
      "type": "body-text",
      "blocks": {
        "f8b6a3b2-35cf-4b78-83fc-94a7081f6786": {
          "type": "title",
          "settings": {
            "title": "If you’re interested in getting a suit adapted for yourself or someone else, please apply through the link below."
          }
        }
      },
      "block_order": [
        "f8b6a3b2-35cf-4b78-83fc-94a7081f6786"
      ],
      "settings": {
      }
    },
    "1641379861d61e8e49": {
      "type": "html",
      "settings": {
        "html": "<button data-tf-popup=\"c5ZfHVYm\" data-tf-iframe-props=\"title=The Wetsuit Project\" style=\"display:inline-block;max-width:100%;white-space:nowrap;overflow:hidden;text-overflow:ellipsis;background-color:#E7DDBB;color:#000000;border-radius:0px;padding:0 33px;height:3.5rem;cursor:pointer;line-height:50px;text-align:center;margin:0;text-decoration:none;\">Apply for a Wetsuit<\/button><script src=\"\/\/embed.typeform.com\/next\/embed.js\"><\/script>"
      }
    }
  },
  "order": [
    "main-titles",
    "16409455489a885bbc",
    "1640945552a6004e0a",
    "16409461148f1ff1bd",
    "1640946239e9f0e095",
    "1640946277aef9214f",
    "164094628093a46417",
    "1641379861d61e8e49"
  ]
}